MANIFEST.in
README.md
logtime
lt
setup.cfg
setup.py
logtime_cli/__init__.py
logtime_cli/logfile_data.py
logtime_cli/logfile_io.py
logtime_cli/logfile_notes_data.py
logtime_cli/logtime.py
logtime_cli/logtime_config.py
logtime_cli.egg-info/PKG-INFO
logtime_cli.egg-info/SOURCES.txt
logtime_cli.egg-info/dependency_links.txt
logtime_cli.egg-info/requires.txt
logtime_cli.egg-info/top_level.txt
logtime_cli/config/config-default.ini
logtime_cli/statistics/__init__.py
logtime_cli/statistics/logfile_pie.py
tests/__init__.py
tests/test_logfile_data.py
tests/test_logfile_notes_data.py