Metadata-Version: 1.2
Name: logtime-cli
Version: 1.5.2
Summary: CLI utility for logging the time you spend on things
Home-page: https://github.com/K-Fitzpatrick/logtime-cli
Author: Kyle Fitzpatrick
Author-email: kyle.a.fitzpatrick@gmail.com
License: UNKNOWN
Platform: UNKNOWN
Requires-Python: >=2,<4
